wintun.cp310-win_amd64.pyd
python_wintun-0.14.2.dist-info/COPYING
python_wintun-0.14.2.dist-info/METADATA
python_wintun-0.14.2.dist-info/WHEEL
python_wintun-0.14.2.dist-info/top_level.txt
python_wintun-0.14.2.dist-info/RECORD
